README.md
mlops_core/bootstrap.py
mlops_core/connectivity/networking.py
mlops_core/connector/remote_storage.py
mlops_core/detection/project_configurations.py
mlops_core/detection/project_structure.py
mlops_core/generator/project_generator.py
mlops_core/runtime.py
mlops_core/utils/conversions.py
mlops_core/utils/strings.py
templates/ISSUE_TEMPLATE.md.jinja
templates/PULL_REQUEST_TEMPLATE.md.jinja
templates/README.md.jinja
templates/devcontainer.json
mlops_core-0.2.6.dist-info/METADATA
mlops_core-0.2.6.dist-info/WHEEL
mlops_core-0.2.6.dist-info/RECORD
