Metadata-Version: 2.1
Name: mlops-core
Version: 0.2.6
Summary: 
Author: Anirudh Aggarwal
Author-email: ani1797@users.noreply.github.com
Requires-Python: >=3.10.6,<4.0.0
Classifier: Programming Language :: Python :: 3
Classifier: Programming Language :: Python :: 3.11
Requires-Dist: azure-identity (>=1.12.0,<2.0.0)
Requires-Dist: dnspython (>=2.3.0,<3.0.0)
Requires-Dist: jinja2 (>=3.1.2,<4.0.0)
Requires-Dist: kaggle (>=1.5.13,<2.0.0)
Requires-Dist: pandas (>=2.0.1,<3.0.0)
Requires-Dist: pyspark (>=3.4.0,<4.0.0)
Requires-Dist: pyyaml (>=6.0,<7.0)
Requires-Dist: tomli (>=2.0.1,<3.0.0)
